kelner/__init__.py
kelner/cli.py
kelner/client.py
kelner/imagenet.py
kelner/model.py
kelner/server.py
kelner/utils.py
kelner/models/__init__.py
kelner/models/kelner_model.py
kelner/models/keras_model.py
kelner/models/tensorflow_model.py
kelner-0.1.5.dist-info/DESCRIPTION.rst
kelner-0.1.5.dist-info/METADATA
kelner-0.1.5.dist-info/RECORD
kelner-0.1.5.dist-info/WHEEL
kelner-0.1.5.dist-info/entry_points.txt
kelner-0.1.5.dist-info/metadata.json
kelner-0.1.5.dist-info/top_level.txt
