Metadata-Version: 2.0
Name: kelner
Version: 0.1.5
Summary: Serve your models
Home-page: https://github.com/lunardog/kelner
Author: Leszek Rybicki
Author-email: leszek-rybicki@cookpad.com
License: BSD
Platform: any
Classifier: Development Status :: 4 - Beta
Classifier: Environment :: Console
Classifier: Intended Audience :: Developers
Classifier: License :: OSI Approved :: BSD License
Classifier: Operating System :: POSIX
Classifier: Operating System :: MacOS
Classifier: Operating System :: Unix
Classifier: Operating System :: Microsoft :: Windows
Classifier: Programming Language :: Python
Classifier: Programming Language :: Python :: 2
Classifier: Programming Language :: Python :: 3
Classifier: Topic :: Software Development :: Libraries :: Python Modules
Requires-Dist: click (>=5.0)
Requires-Dist: Keras (>=2.0.0)
Requires-Dist: h5py
Requires-Dist: numpy (>=1.0)
Requires-Dist: requests
Requires-Dist: boto3
Requires-Dist: python-datauri
Requires-Dist: Pillow (>=4.0)
